sensai_labs/__init__.py
sensai_labs/agents/__init__.py
sensai_labs/agents/framework/__init__.py
sensai_labs/agents/framework/base.py
sensai_labs/agents/framework/result_handler.py
sensai_labs/agents/framework/runner.py
sensai_labs/agents/framework/types.py
sensai_labs/agents/framework/utils.py
sensai_labs-0.1.3.dist-info/licenses/LICENSE
sensai_labs-0.1.3.dist-info/METADATA
sensai_labs-0.1.3.dist-info/WHEEL
sensai_labs-0.1.3.dist-info/top_level.txt
sensai_labs-0.1.3.dist-info/RECORD
